tarkov_market/__init__.py
tarkov_market/client.py
tarkov_market/enums.py
tarkov_market/errors.py
tarkov_market/item.py
tarkov_market/requester.py
tarkov_market/traders.py
tarkov_market/utils.py
tarkov_market/types/__init__.py
tarkov_market/types/item.py
tarkov_market/types/trader.py
tarkov_market.py-0.15.2.dist-info/LICENSE
tarkov_market.py-0.15.2.dist-info/METADATA
tarkov_market.py-0.15.2.dist-info/WHEEL
tarkov_market.py-0.15.2.dist-info/top_level.txt
tarkov_market.py-0.15.2.dist-info/RECORD
