Metadata-Version: 2.1
Name: tarkov-market.py
Version: 0.15.2
Summary: async API wrapper for Tarkov Market written in Python.
Home-page: https://github.com/Hostagen/tarkov-market.py
Author: Hostagen
License: MIT
Requires-Python: >=3.8.0
License-File: LICENSE
